mb_mercately_client/__init__.py
mb_mercately_client/async_client.py
mb_mercately_client/client.py
mb_mercately_client/exceptions.py
mb_mercately_client/models.py
mb_mercately_client-0.4.0.dist-info/METADATA
mb_mercately_client-0.4.0.dist-info/WHEEL
mb_mercately_client-0.4.0.dist-info/top_level.txt
mb_mercately_client-0.4.0.dist-info/RECORD
